[{"id":0,"nameQ":"Découvrir le forum","idPnj":28,"speaker":28,"dialInit":"Bonjour, essaye de trouver les bâtiments A, B et E puis reviens me parler ensuite","dialQ":"Tu n'as pas encore trouvé tous les bâtiments, reviens quand ce sera le cas !","dialEnd":"Bravo, les bâtiments n'ont plus de secret pour toi","dialEnded":"Comme tu le sais maintenant, tu es ici au forum.","QEforDispo":[],"QCforDispo":[],"QneededToEnd":[1,2,3]},{"id":1,"nameQ":"Découvrir le bâtiment A","idPnj":26,"speaker":26,"dialInit":"","dialQ":"","dialEnd":"Bravo, tu as trouvé le bâtiment A","dialEnded":"Tu es dans le bâtiment A, où se trouve notamment le service des stages","QEforDispo":[],"QCforDispo":[0],"QneededToEnd":[]},{"id":2,"nameQ":"Découvrir le bâtiment B","idPnj":25,"speaker":25,"dialInit":"","dialQ":"","dialEnd":"Bravo, tu as trouvé le bâtiment B","dialEnded":"Tu es dans le bâtiment B, où se trouvent les salles informatiques","QEforDispo":[],"QCforDispo":[0],"QneededToEnd":[]},{"id":3,"nameQ":"Découvrir le bâtiment E","idPnj":27,"speaker":27,"dialInit":"","dialQ":"","dialEnd":"Bravo, tu as trouvé le bâtiment E","dialEnded":"Tu es dans le bâtiment E","QEforDispo":[],"QCforDispo":[0],"QneededToEnd":[]}]